fim/__init__.py
fim/fim.py
find_improved-1.0.dist-info/DESCRIPTION.rst
find_improved-1.0.dist-info/METADATA
find_improved-1.0.dist-info/RECORD
find_improved-1.0.dist-info/WHEEL
find_improved-1.0.dist-info/entry_points.txt
find_improved-1.0.dist-info/metadata.json
find_improved-1.0.dist-info/top_level.txt
